websocket_training/__init__.py
websocket_training/main.py
websocket_training/templates/chat.html
websocket_training/ws_router/README.md
websocket_training/ws_router/__init__.py
websocket_training/ws_router/connect.py
websocket_training/ws_router/manager.py
websocket_training/ws_router/router.py
websocket_training/ws_router/test_ws.http
websocket_training-0.1.8.dist-info/METADATA
websocket_training-0.1.8.dist-info/WHEEL
websocket_training-0.1.8.dist-info/RECORD
